yaststool/__init__.py
yaststool/main.py
yaststool-0.1.1.dist-info/entry_points.txt
yaststool-0.1.1.dist-info/LICENSE
yaststool-0.1.1.dist-info/WHEEL
yaststool-0.1.1.dist-info/METADATA
yaststool-0.1.1.dist-info/RECORD
